bsmap/__init__.py
bsmap/analysis.py
bsmap/autolights.py
bsmap/custom_data.py
bsmap/mapper.py
bsmap/models.py
bsmap/operations.py
bsmap/templates.py
bsmap/utils.py
bsmap-1.1.4.dist-info/METADATA
bsmap-1.1.4.dist-info/WHEEL
bsmap-1.1.4.dist-info/top_level.txt
bsmap-1.1.4.dist-info/RECORD
